{
  "$schema": "../node_modules/@tauri-apps/cli/config.schema.json",
  "productName": "thisdotssh",
  "version": "1.1.0",
  "identifier": "com.this-dot-ssh.dev",
  "build": {
    "frontendDist": "../dist",
    "devUrl": "http://localhost:3000",
    "beforeDevCommand": "npm run dev",
    "beforeBuildCommand": "npm run generate"
  },
  "app": {
    "windows": [
      {
        "title": "this.ssh",
        "width": 450,
        "height": 650,
        "resizable": true,
        "fullscreen": false
      }
    ],
    "security": {
      "csp": null
    }
  },
  "bundle": {
    "active": true,
    "targets": "all",
    "icon": [
      "icons/32x32.png",
      "icons/128x128.png",
      "icons/128x128@2x.png",
      "icons/icon.icns",
      "icons/icon.ico"
    ]
  }
}